as_models/__init__.py
as_models/__main__.py
as_models/constants.py
as_models/context.py
as_models/exceptions.py
as_models/log_levels.py
as_models/manifest.py
as_models/model_state.py
as_models/models.py
as_models/ports.py
as_models/sentinel.py
as_models/stats.py
as_models/util.py
as_models/version.py
as_models/web_api.py
as_models/api_support/__init__.py
as_models/api_support/pydap_patches.py
as_models/api_support/retries.py
as_models/api_support/xr.py
as_models/runtime/__init__.py
as_models/runtime/matlab.py
as_models/runtime/python.py
as_models/runtime/r.py
as_models/runtime/runtime.py
as_models/runtime/subprocess.py
as_models/testing/__init__.py
as_models/testing/context.py
as_models/testing/mock.py
as_models/testing/ssl.py
eratos_as_api-4.5.0.dist-info/METADATA
eratos_as_api-4.5.0.dist-info/WHEEL
eratos_as_api-4.5.0.dist-info/licenses/LICENSE
eratos_as_api-4.5.0.dist-info/RECORD
