Metadata-Version: 2.4
Name: eratos-as-api
Version: 4.5.0
Summary: Analysis Services model integration library.
Project-URL: Homepage, https://bitbucket.csiro.au/projects/SC/repos/as-models-api/browse
Author-email: Mac Coombe <mac.coombe@csiro.au>
Maintainer-email: Eratos <support@eratos.com>
License: MIT License
License-File: LICENSE
Keywords: models
Classifier: Development Status :: 3 - Alpha
Classifier: Intended Audience :: Developers
Classifier: License :: OSI Approved :: MIT License
Classifier: Natural Language :: English
Classifier: Operating System :: POSIX
Classifier: Programming Language :: Python :: 3
Classifier: Programming Language :: Python :: 3.7
Classifier: Programming Language :: Python :: 3.8
Classifier: Programming Language :: Python :: 3.9
Classifier: Programming Language :: Python :: 3.10
Classifier: Programming Language :: Python :: 3.11
Classifier: Programming Language :: Python :: 3.12
Classifier: Topic :: Scientific/Engineering :: Information Analysis
Requires-Python: >=3.7
Requires-Dist: flask==2.2.3
Requires-Dist: werkzeug<3.0.0,>=2.2.2
Provides-Extra: r
Requires-Dist: rpy2==3.3.3; extra == 'r'
Provides-Extra: test
Requires-Dist: httpretty==1.1.4; extra == 'test'
Requires-Dist: rpy2==3.3.3; extra == 'test'
Requires-Dist: webob==1.8.7; extra == 'test'
Requires-Dist: xarray==0.18.0; extra == 'test'
